{
  "packages": [
    {
      "name": "etherkit",
      "maintainer": "Etherkit",
      "websiteURL": "https://www.etherkit.com",
      "email": "support@etherkit.com",
      "help": {
        "online": "https://www.etherkit.com/docs"
      },
      "platforms": [
        {
          "name": "Etherkit SAMD Boards",
          "architecture": "samd",
          "version": "1.0.0",
          "category": "Etherkit",
          "help": {
            "online": "https://www.etherkit.com/docs"
          },
          "url": "https://etherkit.github.io/arduino/etherkit-samd-1.0.0.tar.gz",
          "archiveFileName": "etherkit-samd-1.0.0.tar.gz",
          "checksum": "SHA-256:26d4ea7dc98335edb950dee461abccc0ced7c0e3673a3ccf8ef44eff75e1aa2c",
          "size": "238848",
          "boards": [
            {"name": "OpenBeacon 2"},
          ],
          "toolsDependencies": [
          ]
        }
      ],
      "tools": [
      ]
    }
  ]
}
